tefasfon/__init__.py
tefasfon/data_fetcher.py
tefasfon/metrics.py
tefasfon/setup_webdriver.py
tefasfon/utils.py
tefasfon-0.4.1.dist-info/LICENSE
tefasfon-0.4.1.dist-info/METADATA
tefasfon-0.4.1.dist-info/WHEEL
tefasfon-0.4.1.dist-info/top_level.txt
tefasfon-0.4.1.dist-info/RECORD
