Metadata-Version: 2.1
Name: tefasfon
Version: 0.4.1
Summary: Fetches fund data from the TEFAS website.
Home-page: https://github.com/urazakgul/tefasfon
Author: Uraz Akgül
Author-email: urazdev@gmail.com
License: MIT
Classifier: Programming Language :: Python :: 3
Classifier: License :: OSI Approved :: MIT License
Requires-Python: >=3.8
License-File: LICENSE
Requires-Dist: requests
Requires-Dist: pandas
Requires-Dist: openpyxl
Requires-Dist: selenium
Requires-Dist: rich
Requires-Dist: lxml
Requires-Dist: webdriver-manager
